<list>
  <Paciente.Paciente>
    <MES__DE__FEVEREIRO>2</MES__DE__FEVEREIRO>
    <nome>rodolfo</nome>
    <cpf>123.123.100-22</cpf>
    <endereco>
      <rua>dasda</rua>
      <complemento>sdsada</complemento>
      <bairro>asdadsa</bairro>
      <cidade>asdadsadasdas</cidade>
      <estado>dasdsadsadsa</estado>
      <cep>01232-231</cep>
      <numero>323</numero>
    </endereco>
    <foneResidencial>
      <telefone>(12)1233-1231</telefone>
    </foneResidencial>
    <foneComercial>
      <telefone>(11)1111-1111</telefone>
    </foneComercial>
    <foneCelular>
      <telefone>(22)2222-2222</telefone>
    </foneCelular>
    <dataDeNascimento>02/09/2010</dataDeNascimento>
    <idade>0</idade>
    <email>xds@gmail.com</email>
    <formaDeContato>Telefone comercial</formaDeContato>
    <dataDaUltimaVisita>02/09/2010</dataDaUltimaVisita>
    <horarioDeAtendimento>
      <AJUSTE__CALENDARIO>1</AJUSTE__CALENDARIO>
      <numeroDeIdentificao>418</numeroDeIdentificao>
      <retorno>false</retorno>
      <primeiraConsulta>false</primeiraConsulta>
      <planoDeSaude>
        <STRING__VAZIA></STRING__VAZIA>
        <precoDoPlano>2.0</precoDoPlano>
        <nomeDoPlano>novo plano</nomeDoPlano>
        <telefoneDoPlano>(22)1234-1234</telefoneDoPlano>
      </planoDeSaude>
    </horarioDeAtendimento>
  </Paciente.Paciente>
  <Paciente.Paciente>
    <MES__DE__FEVEREIRO>2</MES__DE__FEVEREIRO>
    <nome>novo paciente</nome>
    <cpf>123.123.213-21</cpf>
    <endereco>
      <rua>rua aew</rua>
      <complemento></complemento>
      <bairro>bairorr</bairro>
      <cidade>cidade</cidade>
      <estado>BA</estado>
      <cep>12313-123</cep>
      <numero>10</numero>
    </endereco>
    <foneResidencial>
      <telefone>(02)3130-2139</telefone>
    </foneResidencial>
    <foneComercial>
      <telefone>(23)0213-0210</telefone>
    </foneComercial>
    <foneCelular>
      <telefone>(12)3132-1312</telefone>
    </foneCelular>
    <dataDeNascimento>02/10/2010</dataDeNascimento>
    <idade>0</idade>
    <email>dasdasdas@emgil.com</email>
    <formaDeContato>Telefone celular</formaDeContato>
    <horarioDeAtendimento>
      <AJUSTE__CALENDARIO>1</AJUSTE__CALENDARIO>
      <numeroDeIdentificao>0</numeroDeIdentificao>
      <retorno>false</retorno>
      <primeiraConsulta>false</primeiraConsulta>
      <planoDeSaude>
        <STRING__VAZIA></STRING__VAZIA>
        <precoDoPlano>100.0</precoDoPlano>
        <nomeDoPlano>nomeDeUmPlano</nomeDoPlano>
        <telefoneDoPlano>(12)1234-1111</telefoneDoPlano>
      </planoDeSaude>
    </horarioDeAtendimento>
  </Paciente.Paciente>
  <Paciente.Paciente>
    <MES__DE__FEVEREIRO>2</MES__DE__FEVEREIRO>
    <nome>paciente aew</nome>
    <cpf>123.131.232-13</cpf>
    <endereco>
      <rua>vanei</rua>
      <complemento></complemento>
      <bairro>IRRO</bairro>
      <cidade>cidades</cidade>
      <estado>BA</estado>
      <cep>03203-203</cep>
      <numero>9</numero>
    </endereco>
    <foneResidencial>
      <telefone>(13)2031-0230</telefone>
    </foneResidencial>
    <foneComercial>
      <telefone>(03)2103-0210</telefone>
    </foneComercial>
    <foneCelular>
      <telefone>(03)0123-0120</telefone>
    </foneCelular>
    <dataDeNascimento>20/10/2010</dataDeNascimento>
    <idade>0</idade>
    <email>email@gmai.com</email>
    <formaDeContato>Telefone comercial</formaDeContato>
    <horarioDeAtendimento>
      <AJUSTE__CALENDARIO>1</AJUSTE__CALENDARIO>
      <numeroDeIdentificao>0</numeroDeIdentificao>
      <retorno>false</retorno>
      <primeiraConsulta>false</primeiraConsulta>
      <planoDeSaude>
        <STRING__VAZIA></STRING__VAZIA>
        <nomeDoPlano>Particular</nomeDoPlano>
      </planoDeSaude>
    </horarioDeAtendimento>
  </Paciente.Paciente>
  <Paciente.Paciente>
    <MES__DE__FEVEREIRO>2</MES__DE__FEVEREIRO>
    <nome>Luiz</nome>
    <cpf>000.000.000-00</cpf>
    <endereco>
      <rua>dsadsadas</rua>
      <complemento>dasdasdasd</complemento>
      <bairro>dasdadasd</bairro>
      <cidade>dasdasdas</cidade>
      <estado>AP</estado>
      <cep>10414-717</cep>
      <numero>10</numero>
    </endereco>
    <foneResidencial>
      <telefone>(17)4171-7717</telefone>
    </foneResidencial>
    <foneComercial>
      <telefone>(17)7171-7171</telefone>
    </foneComercial>
    <foneCelular>
      <telefone>(88)5555-5555</telefone>
    </foneCelular>
    <dataDeNascimento>02/02/2002</dataDeNascimento>
    <idade>8</idade>
    <email>luiz@gmail.com</email>
    <formaDeContato>Email</formaDeContato>
    <horarioDeAtendimento>
      <AJUSTE__CALENDARIO>1</AJUSTE__CALENDARIO>
      <numeroDeIdentificao>0</numeroDeIdentificao>
      <retorno>false</retorno>
      <primeiraConsulta>false</primeiraConsulta>
      <planoDeSaude>
        <STRING__VAZIA></STRING__VAZIA>
        <precoDoPlano>103.0</precoDoPlano>
        <nomeDoPlano>mais dois mil</nomeDoPlano>
        <telefoneDoPlano>(12)3213-2131</telefoneDoPlano>
      </planoDeSaude>
    </horarioDeAtendimento>
  </Paciente.Paciente>
</list>